vtools/__init__.py
vtoolscd-1.6.dist-info/METADATA
vtoolscd-1.6.dist-info/WHEEL
vtoolscd-1.6.dist-info/top_level.txt
vtoolscd-1.6.dist-info/zip-safe
vtoolscd-1.6.dist-info/RECORD
