Metadata-Version: 2.1
Name: vtoolscd
Version: 1.6
Summary: Manage vitual machines, getting some informations (eg. OS).
Home-page: https://github.com/CastellaniDavide/vtools
Author: CastellaniDavide
Author-email: help@castellanidavide.it
License: GNU
Platform: linux_distibution
Requires-Python: >=3.6
Requires-Dist: tabular-log
Requires-Dist: requests
Requires-Dist: programGUI (>=1.4)
